micro_vad_cpp.cpython-38-x86_64-linux-gnu.so
pymicro_vad/__init__.py
pymicro_vad2-1.0.2.dist-info/LICENSE
pymicro_vad2-1.0.2.dist-info/METADATA
pymicro_vad2-1.0.2.dist-info/WHEEL
pymicro_vad2-1.0.2.dist-info/top_level.txt
pymicro_vad2-1.0.2.dist-info/RECORD
