Metadata-Version: 2.1
Name: pymicro_vad2
Version: 1.0.2
Summary: Self-contained voice activity detector
Home-page: https://github.com/Brishen/pymicro-vad
Author: Michael Hansen
Author-email: Michael Hansen <mike@rhasspy.org>
License: Apache-2.0
Project-URL: Homepage, https://github.com/Brishen/pymicro-vad
Project-URL: Bug Tracker, https://github.com/Brishen/pymicro-vad/issues
Classifier: License :: OSI Approved :: Apache Software License
Classifier: Programming Language :: Python :: 3
Classifier: Programming Language :: Python :: 3.7
Classifier: Programming Language :: Python :: 3.8
Classifier: Programming Language :: Python :: 3.9
Classifier: Programming Language :: Python :: 3.10
Classifier: Programming Language :: Python :: 3.11
Classifier: Programming Language :: Python :: 3.12
Classifier: Programming Language :: Python :: 3.13
Requires-Python: >=3.7
License-File: LICENSE
